onnx_mxnet/__init__.py
onnx_mxnet/backend.py
onnx_mxnet/backend_rep.py
onnx_mxnet/common.py
onnx_mxnet/import_helper.py
onnx_mxnet/import_onnx.py
onnx_mxnet/tests/__init__.py
onnx_mxnet/tests/onnx_backend_test.py
onnx_mxnet/tests/test_layers.py
onnx_mxnet/tests/test_models.py
onnx_mxnet/tests/test_super_resolution.py
onnx_mxnet-0.4.2.dist-info/DESCRIPTION.rst
onnx_mxnet-0.4.2.dist-info/METADATA
onnx_mxnet-0.4.2.dist-info/RECORD
onnx_mxnet-0.4.2.dist-info/WHEEL
onnx_mxnet-0.4.2.dist-info/metadata.json
onnx_mxnet-0.4.2.dist-info/top_level.txt
