Metadata-Version: 2.0
Name: onnx-mxnet
Version: 0.4.2
Summary: ONNX-MXNet Model converter
Home-page: https://github.com/onnx/onnx-mxnet
Author: UNKNOWN
Author-email: UNKNOWN
License: Apache 2.0
Keywords: ONNX MXNet model converter deep learning
Platform: UNKNOWN
Requires-Dist: mxnet (>=0.11.0)
Requires-Dist: onnx (>=1.0.1)
